ortho_modificator/__init__.py
ortho_modificator/common.py
ortho_modificator/foliumap.py
ortho_modificator/ortho_modificator.py
ortho_modificator-0.1.0.dist-info/licenses/LICENSE
ortho_modificator-0.1.0.dist-info/METADATA
ortho_modificator-0.1.0.dist-info/WHEEL
ortho_modificator-0.1.0.dist-info/entry_points.txt
ortho_modificator-0.1.0.dist-info/top_level.txt
ortho_modificator-0.1.0.dist-info/RECORD
